{
  "formatVersion": 0,
  "uid": "powercrystals.core",
  "version": "44",
  "time": 1363336617000,
  "data": {
    "general.launcher": "minecraft",
    "general.downloads": [
      {
        "type": "general.file",
        "url": "http://build.technicpack.net/job/PowerCrystalsCore/44//artifact/build/dist/PowerCrystalsCore-1.1.0B1-44.jar",
        "size": 104901,
        "sha256": "341715e0d81e54d86b386e7080e3833d492637efefeb0c97fcb94cccfba800e3",
        "destination": "mods/powercrystals.core-44.jar"
      }
    ]
  }
}