{
  "formatVersion": 0,
  "uid": "creepercollateral",
  "version": "1.0.0B3-6",
  "time": "1422655744",
  "type": "Release",
  "data": [
    {
      "general.downloads": [
        {
          "url": "http://curse.com/mc-mods/minecraft/223801-creepercollateral/2225858",
          "size": null,
          "sha256": null,
          "destination": "mods/creepercollateral-1.0.0B3-6.jar"
        }
      ]
    }
  ],
  "requires": [
    {
      "uid": "net.minecraft",
      "version": "1.7.10"
    }
  ]
}