{
  "formatVersion": 0,
  "uid": "alchemyplusplus",
  "version": "35",
  "time": 1414387390000,
  "data": {
    "general.launcher": "minecraft",
    "general.downloads": [
      {
        "type": "general.file",
        "url": "http://jenkins.jakimfett.com/job/AlchemyPlusPlus%201.7/35//artifact/output/AlchemyPlusPlus-1.7.10-1.2.0.35.jar",
        "size": 176674,
        "sha256": "fddd3c03d6027f8beeb9819d196865bf772941ff1bc57a4e4d5c64e171e886e6",
        "destination": "mods/alchemyplusplus-35.jar"
      }
    ]
  }
}