{
  "formatVersion": 0,
  "uid": "openmodslib",
  "version": "221",
  "time": 1407315918000,
  "client": {
    "rules": [
      {
        "action": "disallow"
      },
      {
        "action": "allow",
        "side": "client"
      }
    ],
    "general.launcher": "minecraft"
  },
  "server": {
    "rules": [
      {
        "action": "disallow"
      },
      {
        "action": "allow",
        "side": "server"
      }
    ],
    "general.launcher": "minecraft"
  },
  "common": {
    "general.launcher": "minecraft",
    "general.downloads": [
      {
        "url": "http://www.openmods.info:8080/job/OpenModsLib/221/artifact/build/libs/OpenModsLib-1.7.10-0.6-snapshot-221.jar",
        "size": null,
        "sha256": null,
        "destination": "mods/openmodslib-221.jar"
      }
    ]
  }
}