{
  "formatVersion": 0,
  "uid": "openperipheralsaddons",
  "version": "106",
  "time": 1400529730000,
  "data": {
    "general.launcher": "minecraft",
    "general.downloads": [
      {
        "type": "general.file",
        "url": "http://www.openmods.info:8080/job/OpenPeripheralAddons/106//artifact/build/libs/OpenPeripheralAddons-1.6.4-0.1.4-snapshot-106.jar",
        "size": 274241,
        "sha256": "87d03df94eb10b1c95ed5bd0f6b15549b27171c346b44a48f5496b0b13c7bb5d",
        "destination": "mods/openperipheralsaddons-106.jar"
      }
    ]
  }
}