{
  "formatVersion": 0,
  "uid": "codechicken.lib",
  "version": "1.0.0.53",
  "time": 1391371720,
  "requires": [
    {
      "uid": "net.minecraft",
      "version": "1.6.4"
    }
  ],
  "client": {
    "general.launcher": "minecraft"
  },
  "server": {
    "general.launcher": "minecraft"
  },
  "common": {
    "general.launcher": "minecraft",
    "general.downloads": [
      {
        "url": "http://files.minecraftforge.net/CodeChickenLib/CodeChickenLib-universal-1.6.4-1.0.0.53.jar",
        "size": null,
        "sha256": null,
        "destination": "mods/codechicken.lib-1.0.0.53.jar"
      }
    ]
  }
}