{
  "formatVersion": 0,
  "uid": "ic2",
  "version": "590",
  "time": 1408073593000,
  "client": {
    "general.launcher": "minecraft"
  },
  "server": {
    "general.launcher": "minecraft"
  },
  "common": {
    "general.launcher": "minecraft",
    "general.downloads": [
      {
        "url": "http://jenkins.ic2.player.to/job/IC2_experimental/590/artifact/build/libs/industrialcraft-2-2.2.590-experimental.jar",
        "size": null,
        "sha256": null,
        "destination": "mods/ic2-590.jar"
      }
    ]
  }
}