{
  "formatVersion": 0,
  "uid": "morpheus",
  "version": "24",
  "time": 1413373673000,
  "data": [
    {
      "rules": [
        {
          "action": "disallow"
        },
        {
          "action": "allow",
          "side": "client"
        }
      ],
      "general.launcher": "minecraft"
    },
    {
      "rules": [
        {
          "action": "disallow"
        },
        {
          "action": "allow",
          "side": "server"
        }
      ],
      "general.launcher": "minecraft"
    },
    {
      "general.launcher": "minecraft"
    }
  ]
}