{
  "formatVersion": 0,
  "uid": "sanguimancy",
  "version": "20",
  "time": 1423165032504,
  "data": [
    {
      "rules": [
        {
          "action": "disallow"
        },
        {
          "action": "allow",
          "side": "client"
        }
      ],
      "general.launcher": "minecraft"
    },
    {
      "rules": [
        {
          "action": "disallow"
        },
        {
          "action": "allow",
          "side": "server"
        }
      ],
      "general.launcher": "minecraft"
    },
    {
      "general.launcher": "minecraft",
      "general.downloads": [
        {
          "url": "http://tehnut.info/jenkins/job/Sanguimancy/20/artifact/build/libs/Sanguimancy-1.7.10-1.1.9Pre-20.jar",
          "size": null,
          "sha256": null,
          "destination": "mods/sanguimancy-20.jar"
        }
      ]
    }
  ]
}