{
  "formatVersion": 0,
  "uid": "galacticraft",
  "version": "183",
  "time": 1410020206000,
  "data": {
    "general.launcher": "minecraft",
    "general.downloads": [
      {
        "type": "general.file",
        "url": "http://2.iongaming.org:8080/job/Galacticraft-1.7/183//artifact/Forge/build/libs/Galacticraft-Planets-BETA-1.7-3.0.2.183.jar",
        "size": 3150932,
        "sha256": "ff770ed2e95ba0ff0dc2f65d6c7817d6c15a34d39d887f7fdcaabf52dbf4915e",
        "destination": "mods/galacticraft-183.jar"
      }
    ]
  }
}