{
  "formatVersion": 0,
  "uid": "galacticraft",
  "version": "245",
  "time": 1417967432000,
  "data": {
    "general.launcher": "minecraft",
    "general.downloads": [
      {
        "type": "general.file",
        "url": "http://2.iongaming.org:8080/job/Galacticraft-1.7/245//artifact/Forge/build/libs/Galacticraft-Planets-1.7-3.0.6.245.jar",
        "size": 3246383,
        "sha256": "ebf45c9e9785ab0c1cd98f5a2f4aec972cfb5d86a2c4664a2bd0c854ed10bd77",
        "destination": "mods/galacticraft-245.jar"
      }
    ]
  }
}