{
  "formatVersion": 0,
  "uid": "compactsolars",
  "version": "3.0.4.14",
  "time": 1351381342,
  "requires": [
    {
      "uid": "net.minecraft"
    }
  ],
  "client": {
    "general.launcher": "minecraft"
  },
  "server": {
    "general.launcher": "minecraft"
  },
  "common": {
    "general.launcher": "minecraft",
    "general.downloads": [
      {
        "url": "http://files.minecraftforge.net/CompactSolars/compactsolars-main-3.0.4.14.zip",
        "size": null,
        "sha256": null,
        "destination": "mods/compactsolars-3.0.4.14.jar"
      }
    ]
  }
}