{
  "formatVersion": 0,
  "uid": "forgeessentials",
  "version": "0.1.0.189",
  "time": 1356921125,
  "requires": [
    {
      "uid": "net.minecraft",
      "version": "1.4.6"
    }
  ],
  "data": {
    "general.launcher": "minecraft",
    "general.downloads": [
      {
        "type": "general.file",
        "url": "http://files.minecraftforge.net/ForgeEssentials/ForgeEssentials-client-1.4.6-0.1.0.189.zip",
        "size": 13502,
        "sha256": "91fa0ef58a0c217a5b3a786d8e3dc77b9902ecbd722c4f6779e30482e2eab19e",
        "destination": "mods/forgeessentials-0.1.0.189.jar"
      }
    ]
  }
}