{
  "formatVersion": 0,
  "uid": "bdew.pressure",
  "version": "27",
  "time": 1411050594000,
  "data": {
    "general.launcher": "minecraft",
    "general.downloads": [
      {
        "type": "general.file",
        "url": "http://jenkins.bdew.net/job/pressure-1.7.10/27//artifact/build/libs/pressure-mc1710-0.9.3.27.jar",
        "size": 540676,
        "sha256": "a7cf5a320651b2904d5457a718d7eb6ae3237cefdecde70af1d00531540970fc",
        "destination": "mods/bdew.pressure-27.jar"
      }
    ]
  }
}