{
  "formatVersion": 0,
  "uid": "forgemultipart",
  "version": "1.0.0.130",
  "time": 1376788693,
  "requires": [
    {
      "uid": "net.minecraft",
      "version": "1.6.2"
    }
  ],
  "data": {
    "general.launcher": "minecraft",
    "general.downloads": [
      {
        "type": "general.file",
        "url": "http://files.minecraftforge.net/ForgeMultipart/ForgeMultipart-universal-1.6.2-1.0.0.130.jar",
        "size": 792247,
        "sha256": "d1baaf6dff45a946b4c8d08562cfc87ed01fb74765583a3faf154085a3ab0ac8",
        "destination": "mods/forgemultipart-1.0.0.130.jar"
      }
    ]
  }
}