{
  "formatVersion": 0,
  "uid": "inventorytweaks",
  "version": "142",
  "time": 1405281071000,
  "client": {
    "general.launcher": "minecraft"
  },
  "server": {
    "general.launcher": "minecraft"
  },
  "common": {
    "general.launcher": "minecraft",
    "general.downloads": [
      {
        "url": "http://build.technicpack.net/job/Inventory-Tweaks/142/artifact/build/libs/InventoryTweaks-1.58-dev-142.jar",
        "size": null,
        "sha256": null,
        "destination": "mods/inventorytweaks-142.jar"
      }
    ]
  }
}